hn
setup.py
hn.egg-info/PKG-INFO
hn.egg-info/SOURCES.txt
hn.egg-info/dependency_links.txt
hn.egg-info/requires.txt
hn.egg-info/top_level.txt
yc/__init__.py
yc/cli.py
yc/core.py
yc/thriftdb.py
yc/times.py