Metadata-Version: 1.1
Name: hn
Version: 0.2.0
Summary: A CLI and Python library for using the HNSearch API.
Home-page: https://github.com/zachwill/hn
Author: Zach Williams
Author-email: hey@zachwill.com
License: MIT
Keywords: hn,ycombinator,hacker news,newsyc
Platform: UNKNOWN
Classifier: Development Status :: 5 - Production/Stable
Classifier: Intended Audience :: Developers
Classifier: Natural Language :: English
Classifier: Operating System :: OS Independent
Classifier: Programming Language :: Python :: 2
Classifier: Topic :: Internet
Classifier: Topic :: Internet :: WWW/HTTP
